nflfastpy/__init__.py
nflfastpy/_version.py
nflfastpy/config.py
nflfastpy/errors.py
nflfastpy/utils.py
nflfastpy-0.0.14.dist-info/METADATA
nflfastpy-0.0.14.dist-info/WHEEL
nflfastpy-0.0.14.dist-info/top_level.txt
nflfastpy-0.0.14.dist-info/RECORD
