Metadata-Version: 2.1
Name: nflfastpy
Version: 0.0.14
Summary: A Python package for loading NFL play by play data, schedule data, roster data, and team logo data from nflfastR
Home-page: https://github.com/fantasydatapros/nflfast_py
Author: Ben Dominguez
Author-email: bendominguez011@gmail.com
License: MIT
Platform: UNKNOWN
Classifier: Programming Language :: Python :: 3
Classifier: License :: OSI Approved :: MIT License
Classifier: Operating System :: OS Independent
Requires-Python: >=3.6
